sparksql_jupyter/__init__.py
sparksql_jupyter/sparksql.py
sparksql_jupyter-0.0.5.dist-info/LICENSE
sparksql_jupyter-0.0.5.dist-info/METADATA
sparksql_jupyter-0.0.5.dist-info/WHEEL
sparksql_jupyter-0.0.5.dist-info/top_level.txt
sparksql_jupyter-0.0.5.dist-info/RECORD
