Metadata-Version: 2.1
Name: sparksql-jupyter
Version: 0.0.5
Summary: Spark SQL magic command for Jupyter notebooks
Home-page: https://github.com/cryeo/sparksql-jupyter
Author: Cinyoung Hur
Author-email: cinyoung.hur@gmail.com
License: MIT License
Classifier: Development Status :: 2 - Pre-Alpha
Classifier: License :: OSI Approved :: MIT License
Classifier: Programming Language :: Python
Classifier: Programming Language :: Python :: 3
Classifier: Programming Language :: Python :: 3.6
Classifier: Topic :: Software Development :: Libraries :: Python Modules
Requires-Python: >=3.6
License-File: LICENSE
Requires-Dist: pyspark >=2.3.0
Requires-Dist: ipython >=7.4.0
Requires-Dist: jinja2 >=3.0.0
